pyp8s/__init__.py
pyp8s/_version.py
pyp8s/metrics.py
tests/__init__.py
tests/test_import.py
pyp8s-3.5.0.dist-info/LICENSE
pyp8s-3.5.0.dist-info/METADATA
pyp8s-3.5.0.dist-info/WHEEL
pyp8s-3.5.0.dist-info/top_level.txt
pyp8s-3.5.0.dist-info/RECORD
