Metadata-Version: 2.1
Name: pyp8s
Version: 3.5.0
Summary: Customisable prometheus exporter for your python application
Home-page: https://github.com/pyp8s/pyp8s
Author: Pavel Kim
Author-email: hello@pavelkim.com
Classifier: Programming Language :: Python :: 3
Classifier: License :: OSI Approved :: GNU General Public License v3 (GPLv3)
Classifier: Operating System :: OS Independent
Requires-Python: >=3.6
License-File: LICENSE
